[
  {
    "backDesc": "I am a teacher. / I was at the store yesterday. / I have been at that store many times.",
    "frontDesc": "Eu sou professor(a). / Estive na loja ontem. / Já estive naquela loja muitas vezes."
  },
  {
    "backDesc": "I want to become a doctor. / I became tired. / I have become more determined.",
    "frontDesc": "Eu quero me tornar médico(a). / Fiquei cansado(a). / Tornei-me mais determinado(a)."
  },
  {
    "backDesc": "I begin a new project. / I began reading a book. / I have begun working on it seriously.",
    "frontDesc": "Eu começo um novo projeto. / Comecei a ler um livro. / Comecei a trabalhar nisso seriamente."
  },
  {
    "backDesc": "I don't want to break the rules. / He broke the branch. / He has broken many rules in the past.",
    "frontDesc": "Não quero quebrar as regras. / Ele quebrou o galho. / Ele já quebrou muitas regras no passado."
  },
  {
    "backDesc": "I bring coffee. / She brought flowers. / She has brought gifts as well.",
    "frontDesc": "Eu trago café. / Ela trouxe flores. / Ela também trouxe presentes."
  },
  {
    "backDesc": "I build a house. / He built a bridge. / He has built many bridges in his career.",
    "frontDesc": "Eu construo uma casa. / Ele construiu uma ponte. / Ele construiu muitas pontes na carreira."
  },
  {
    "backDesc": "I buy new clothes. / She bought a car. / She has bought several cars over the years.",
    "frontDesc": "Eu compro roupas novas. / Ela comprou um carro. / Ela comprou vários carros ao longo dos anos."
  },
  {
    "backDesc": "I can help. / He could come earlier. / He has been able to assist many times.",
    "frontDesc": "Eu posso ajudar. / Ele pôde vir mais cedo. / Ele já conseguiu ajudar muitas vezes."
  },
  {
    "backDesc": "I catch the ball. / He caught a fish. / He has caught many fish in this lake.",
    "frontDesc": "Eu pego a bola. / Ele pegou um peixe. / Ele já pegou muitos peixes neste lago."
  },
  {
    "backDesc": "I choose a dish. / She chose a book. / She has chosen wisely every time.",
    "frontDesc": "Eu escolho um prato. / Ela escolheu um livro. / Ela sempre escolheu com sabedoria."
  },
  {
    "backDesc": "I come to work. / He came earlier. / He has come on time every day.",
    "frontDesc": "Eu venho para o trabalho. / Ele veio mais cedo. / Ele tem chegado pontualmente todos os dias."
  },
  {
    "backDesc": "It costs five dollars. / It cost more yesterday. / It has cost me a fortune so far.",
    "frontDesc": "Isso custa cinco dólares. / Custou mais ontem. / Já me custou uma fortuna até agora."
  },
  {
    "backDesc": "I cut the paper. / He cut the wood. / He has cut many pieces of wood before.",
    "frontDesc": "Eu corto o papel. / Ele cortou a madeira. / Ele já cortou muitas peças de madeira antes."
  },
  {
    "backDesc": "I cast away the old clothes. / He cast the net. / He has cast a net before to catch fish.",
    "frontDesc": "Eu jogo fora as roupas velhas. / Ele lançou a rede. / Ele já lançou uma rede antes para pescar."
  },
  {
    "backDesc": "I do my homework. / He did the dinner. / He has done this type of work before.",
    "frontDesc": "Eu faço minha lição de casa. / Ele fez o jantar. / Ele já fez esse tipo de trabalho antes."
  },
  {
    "backDesc": "I draw a picture. / She drew a landscape. / She has drawn many landscapes.",
    "frontDesc": "Eu desenho uma figura. / Ela desenhou uma paisagem. / Ela já desenhou muitas paisagens."
  },
  {
    "backDesc": "I drink water. / He drank juice. / He has drunk all the juice in the fridge.",
    "frontDesc": "Eu bebo água. / Ele bebeu suco. / Ele já bebeu todo o suco da geladeira."
  },
  {
    "backDesc": "I drive a car. / She drove the bus. / She has driven that route many times.",
    "frontDesc": "Eu dirijo um carro. / Ela dirigiu o ônibus. / Ela já dirigiu essa rota muitas vezes."
  },
  {
    "backDesc": "I dwell in Warsaw. / He dwelt there earlier. / He has dwelt in many cities over the years.",
    "frontDesc": "Eu resido em Varsóvia. / Ele residiu lá antes. / Ele já morou em muitas cidades ao longo dos anos."
  },
  {
    "backDesc": "I eat breakfast. / She ate lunch. / She has eaten at this restaurant before.",
    "frontDesc": "Eu tomo café da manhã. / Ela almoçou. / Ela já comeu neste restaurante antes."
  },
  {
    "backDesc": "I fall off the bike. / He fell from the ladder. / He has fallen a few times lately.",
    "frontDesc": "Eu caio da bicicleta. / Ele caiu da escada. / Ele tem caído algumas vezes ultimamente."
  },
  {
    "backDesc": "I feel good. / She felt pain. / She has felt better since then.",
    "frontDesc": "Eu me sinto bem. / Ela sentiu dor. / Ela tem se sentido melhor desde então."
  },
  {
    "backDesc": "I fight for my rights. / He fought in the war. / He has fought bravely for his country.",
    "frontDesc": "Eu luto pelos meus direitos. / Ele lutou na guerra. / Ele tem lutado bravamente pelo seu país."
  },
  {
    "backDesc": "I find the key. / She found the solution. / She has found many solutions so far.",
    "frontDesc": "Eu encontro a chave. / Ela encontrou a solução. / Ela já encontrou muitas soluções até agora."
  },
  {
    "backDesc": "I fly by airplane. / He flew to London. / He has flown internationally many times.",
    "frontDesc": "Eu viajo de avião. / Ele voou para Londres. / Ele já voou para o exterior muitas vezes."
  },
  {
    "backDesc": "I forget the name. / She forgot the keys. / She has forgotten them before.",
    "frontDesc": "Eu esqueço o nome. / Ela esqueceu as chaves. / Ela já esqueceu antes."
  },
  {
    "backDesc": "I get a letter. / He got a gift. / He has gotten many gifts recently.",
    "frontDesc": "Eu recebo uma carta. / Ele recebeu um presente. / Ele tem recebido muitos presentes ultimamente."
  },
  {
    "backDesc": "I give you a gift. / She gave him a book. / She has given many books as presents.",
    "frontDesc": "Eu lhe dou um presente. / Ela deu um livro para ele. / Ela já deu muitos livros de presente."
  },
  {
    "backDesc": "I go to school. / He went to work. / He has gone there every day this week.",
    "frontDesc": "Eu vou à escola. / Ele foi ao trabalho. / Ele tem ido lá todos os dias desta semana."
  },
  {
    "backDesc": "I grind coffee. / He ground the grain. / He has ground coffee beans for years.",
    "frontDesc": "Eu moe café. / Ele moeu o grão. / Ele mói grãos de café há anos."
  },
  {
    "backDesc": "I grow every day. / He grew quickly. / He has grown a lot this year.",
    "frontDesc": "Eu cresço todos os dias. / Ele cresceu rapidamente. / Ele cresceu muito este ano."
  },
  {
    "backDesc": "I have a car. / He had a guitar. / She has had many opportunities to travel.",
    "frontDesc": "Eu tenho um carro. / Ele tinha uma guitarra. / Ela teve muitas oportunidades de viajar."
  },
  {
    "backDesc": "I hear music. / He heard the noise. / He has heard that noise before.",
    "frontDesc": "Eu ouço música. / Ele ouviu o barulho. / Ele já ouviu esse barulho antes."
  },
  {
    "backDesc": "I hide the gift. / She hid the letter. / She has hidden messages in her diary.",
    "frontDesc": "Eu escondo o presente. / Ela escondeu a carta. / Ela tem escondido mensagens em seu diário."
  },
  {
    "backDesc": "I hit the ball. / He hit the door. / He has hit that ball many times.",
    "frontDesc": "Eu bato na bola. / Ele bateu na porta. / Ele já acertou essa bola muitas vezes."
  },
  {
    "backDesc": "I hold the book. / She held the bag. / She has held onto that bag for years.",
    "frontDesc": "Eu seguro o livro. / Ela segurou a bolsa. / Ela mantém essa bolsa há anos."
  },
  {
    "backDesc": "I hurt myself while running. / He hurt his hand. / He has hurt himself multiple times.",
    "frontDesc": "Eu me machuco enquanto corro. / Ele machucou a mão. / Ele já se machucou várias vezes."
  },
  {
    "backDesc": "I keep a secret. / She kept the documents. / She has kept them in a safe place.",
    "frontDesc": "Eu guardo um segredo. / Ela guardou os documentos. / Ela os manteve em um lugar seguro."
  },
  {
    "backDesc": "I know the answer. / He knew the solution. / He has known it all along.",
    "frontDesc": "Eu sei a resposta. / Ele sabia a solução. / Ele sempre soube disso."
  },
  {
    "backDesc": "I learn English. / She learned to dance. / She has learned many languages.",
    "frontDesc": "Eu aprendo inglês. / Ela aprendeu a dançar. / Ela já aprendeu muitos idiomas."
  },
  {
    "backDesc": "I leave the house. / He left the office. / He has left his job recently.",
    "frontDesc": "Eu saio de casa. / Ele saiu do escritório. / Ele deixou o emprego recentemente."
  },
  {
    "backDesc": "I lend a book. / She lent money. / She has lent money to friends before.",
    "frontDesc": "Eu empresto um livro. / Ela emprestou dinheiro. / Ela já emprestou dinheiro a amigos antes."
  },
  {
    "backDesc": "I let you in. / He let her stay. / He has let many people stay at his place.",
    "frontDesc": "Eu deixo você entrar. / Ele a deixou ficar. / Ele já deixou muitas pessoas ficarem na casa dele."
  },
  {
    "backDesc": "I lie on the couch. / He lay on the bed. / He has lain there for hours.",
    "frontDesc": "Eu me deito no sofá. / Ele se deitou na cama. / Ele tem ficado deitado lá por horas."
  },
  {
    "backDesc": "I lose my keys. / He lost his wallet. / He has lost things many times.",
    "frontDesc": "Eu perco minhas chaves. / Ele perdeu a carteira. / Ele já perdeu coisas muitas vezes."
  },
  {
    "backDesc": "I make dinner. / She made a cake. / She has made many delicious cakes.",
    "frontDesc": "Eu faço o jantar. / Ela fez um bolo. / Ela já fez muitos bolos deliciosos."
  },
  {
    "backDesc": "It means something important. / He meant something else. / He has meant it sincerely all along.",
    "frontDesc": "Significa algo importante. / Ele quis dizer outra coisa. / Ele quis dizer isso de forma sincera o tempo todo."
  },
  {
    "backDesc": "I meet with friends. / She met with the manager. / She has met many interesting people.",
    "frontDesc": "Eu encontro amigos. / Ela se encontrou com o gerente. / Ela já conheceu muitas pessoas interessantes."
  },
  {
    "backDesc": "I pay the bills. / He paid for dinner. / He has paid his dues already.",
    "frontDesc": "Eu pago as contas. / Ele pagou o jantar. / Ele já pagou suas dívidas."
  },
  {
    "backDesc": "I put the book on the table. / She put the keys on the shelf. / She has put them there before.",
    "frontDesc": "Eu coloco o livro na mesa. / Ela colocou as chaves na prateleira. / Ela já as colocou lá antes."
  },
  {
    "backDesc": "I read the newspaper. / He read the book. / He has read that book many times.",
    "frontDesc": "Eu leio o jornal. / Ele leu o livro. / Ele já leu esse livro muitas vezes."
  },
  {
    "backDesc": "I ride a bike. / She rode a horse. / She has ridden many horses in her life.",
    "frontDesc": "Eu ando de bicicleta. / Ela montou em um cavalo. / Ela já montou em muitos cavalos na vida."
  },
  {
    "backDesc": "I ring you. / He rang me. / He has rung me every day this week.",
    "frontDesc": "Eu te telefono. / Ele me ligou. / Ele me ligou todos os dias esta semana."
  },
  {
    "backDesc": "The sun rises in the morning. / He rose his hand. / He has risen early every day.",
    "frontDesc": "O sol nasce de manhã. / Ele levantou a mão. / Ele tem se levantado cedo todos os dias."
  },
  {
    "backDesc": "I run every day. / He ran faster. / He has run marathons before.",
    "frontDesc": "Eu corro todos os dias. / Ele correu mais rápido. / Ele já correu maratonas antes."
  },
  {
    "backDesc": "I say the truth. / He said something important. / He has said that many times.",
    "frontDesc": "Eu digo a verdade. / Ele disse algo importante. / Ele já disse isso muitas vezes."
  },
  {
    "backDesc": "I see the stars. / She saw a bird. / She has seen many birds lately.",
    "frontDesc": "Eu vejo as estrelas. / Ela viu um pássaro. / Ela tem visto muitos pássaros ultimamente."
  },
  {
    "backDesc": "I sell a car. / He sold the house. / He has sold several houses this year.",
    "frontDesc": "Eu vendo um carro. / Ele vendeu a casa. / Ele já vendeu várias casas este ano."
  },
  {
    "backDesc": "I send a letter. / She sent a package. / She has sent many packages abroad.",
    "frontDesc": "Eu envio uma carta. / Ela enviou um pacote. / Ela já enviou muitos pacotes para o exterior."
  },
  {
    "backDesc": "I set the alarm for 7 AM. / He set the tables for the party. / He has set them up perfectly.",
    "frontDesc": "Eu programo o alarme para as 7 da manhã. / Ele arrumou as mesas para a festa. / Ele as preparou perfeitamente."
  },
  {
    "backDesc": "I shake my hands when I'm nervous. / He shook his hand in farewell. / He has shaken hands many times.",
    "frontDesc": "Eu tremo as mãos quando estou nervoso(a). / Ele apertou a mão em despedida. / Ele já apertou muitas mãos."
  },
  {
    "backDesc": "The sun shines brightly today. / He shone the lighthouse at night. / He has shone it on the rocks before.",
    "frontDesc": "O sol brilha intensamente hoje. / Ele iluminou o farol à noite. / Ele já iluminou as rochas antes."
  },
  {
    "backDesc": "I shoot with a bow during practice. / He shot a goal in the game. / He has shot many goals this season.",
    "frontDesc": "Eu atiro com arco durante o treino. / Ele fez um gol na partida. / Ele já marcou muitos gols nesta temporada."
  },
  {
    "backDesc": "I show photos from vacation. / He showed his new car. / He has shown it to everyone.",
    "frontDesc": "Eu mostro fotos das férias. / Ele mostrou seu carro novo. / Ele já mostrou para todo mundo."
  },
  {
    "backDesc": "I shut the door before leaving. / He shut the window when it got cold. / He has shut them every night.",
    "frontDesc": "Eu fecho a porta antes de sair. / Ele fechou a janela quando esfriou. / Ele as fecha toda noite."
  },
  {
    "backDesc": "I sing my favorite song. / She sang at the concert. / She has sung there many times.",
    "frontDesc": "Eu canto minha música favorita. / Ela cantou no show. / Ela já cantou lá muitas vezes."
  },
  {
    "backDesc": "The ship sinks in the sea. / He sank during the storm. / It has sunk completely.",
    "frontDesc": "O navio afunda no mar. / Ele afundou durante a tempestade. / Ele afundou completamente."
  },
  {
    "backDesc": "I sit on the chair. / She sat at the table. / She has sat there for hours.",
    "frontDesc": "Eu me sento na cadeira. / Ela se sentou à mesa. / Ela ficou sentada lá por horas."
  },
  {
    "backDesc": "I sleep in my bed. / He slept all night. / He has slept well lately.",
    "frontDesc": "Eu durmo na minha cama. / Ele dormiu a noite toda. / Ele tem dormido bem ultimamente."
  },
  {
    "backDesc": "I speak English. / He spoke at the conference. / He has spoken there twice.",
    "frontDesc": "Eu falo inglês. / Ele falou na conferência. / Ele já falou lá duas vezes."
  },
  {
    "backDesc": "I spend time with my family. / He spent a lot of money on the trip. / He has spent all his savings.",
    "frontDesc": "Eu passo tempo com minha família. / Ele gastou muito dinheiro na viagem. / Ele já gastou todas as economias."
  },
  {
    "backDesc": "I stand at the head of the team. / She stood by the window. / She has stood there quietly.",
    "frontDesc": "Eu fico à frente da equipe. / Ela ficou perto da janela. / Ela permaneceu lá em silêncio."
  },
  {
    "backDesc": "I swim every morning. / He swam in the lake. / He has swum across that lake before.",
    "frontDesc": "Eu nado todas as manhãs. / Ele nadou no lago. / Ele já atravessou esse lago nadando antes."
  },
  {
    "backDesc": "I take my medicine in the morning. / She took an umbrella. / She has taken it with her today.",
    "frontDesc": "Eu tomo meu remédio de manhã. / Ela pegou um guarda-chuva. / Ela o levou consigo hoje."
  },
  {
    "backDesc": "I teach mathematics. / He taught me a new skill. / He has taught many students over the years.",
    "frontDesc": "Eu ensino matemática. / Ele me ensinou uma nova habilidade. / Ele ensinou muitos alunos ao longo dos anos."
  },
  {
    "backDesc": "I always tell him about the change of plans. / She told me a secret. / She has told many secrets over time.",
    "frontDesc": "Eu sempre conto a ele sobre a mudança de planos. / Ela me contou um segredo. / Ela já contou muitos segredos ao longo do tempo."
  },
  {
    "backDesc": "I think about the future. / He thought about solving the problem. / He has thought it through carefully.",
    "frontDesc": "Eu penso no futuro. / Ele pensou em resolver o problema. / Ele já refletiu sobre isso cuidadosamente."
  },
  {
    "backDesc": "I throw the ball into the basket. / She threw the bag on the ground. / She has thrown it away now.",
    "frontDesc": "Eu jogo a bola na cesta. / Ela jogou a bolsa no chão. / Ela já jogou fora agora."
  },
  {
    "backDesc": "I understand this task. / He understood my explanation. / He has understood everything clearly.",
    "frontDesc": "Eu entendo esta tarefa. / Ele entendeu minha explicação. / Ele entendeu tudo claramente."
  },
  {
    "backDesc": "I always wake up early in the morning. / She woke up late. / She has woken up earlier on other days.",
    "frontDesc": "Eu sempre acordo cedo de manhã. / Ela acordou tarde. / Ela já acordou mais cedo em outros dias."
  },
  {
    "backDesc": "I wear a new jacket. / He wore elegant clothes. / He has worn them many times before.",
    "frontDesc": "Eu uso uma jaqueta nova. / Ele vestiu roupas elegantes. / Ele já as vestiu muitas vezes."
  },
  {
    "backDesc": "I win the board game. / She won the contest. / She has won many contests in her life.",
    "frontDesc": "Eu venço o jogo de tabuleiro. / Ela venceu o concurso. / Ela já ganhou muitos concursos na vida."
  },
  {
    "backDesc": "I write a letter to a friend. / He wrote an article. / He has written several articles this month.",
    "frontDesc": "Eu escrevo uma carta para um amigo. / Ele escreveu um artigo. / Ele já escreveu vários artigos neste mês."
  },
  {
    "backDesc": "Problems arise suddenly. / He arose from the problems. / He has arisen to face new challenges.",
    "frontDesc": "Os problemas surgem de repente. / Ele se ergueu dos problemas. / Ele se levantou para enfrentar novos desafios."
  },
  {
    "backDesc": "I always awake earlier. / She awoke from a light sleep. / She has awoken feeling rested.",
    "frontDesc": "Eu sempre desperto mais cedo. / Ela despertou de um sono leve. / Ela tem despertado sentindo-se descansada."
  },
  {
    "backDesc": "I usually bear it well. / He bore many difficulties. / He has borne his burdens with courage.",
    "frontDesc": "Eu geralmente suporto isso bem. / Ele suportou muitas dificuldades. / Ele tem carregado seus fardos com coragem."
  },
  {
    "backDesc": "I beat the drums during the concert. / He beat the record. / He has beaten several records so far.",
    "frontDesc": "Eu toco tambor durante o show. / Ele quebrou o recorde. / Ele já quebrou vários recordes até agora."
  },
  {
    "backDesc": "I bend to reach. / She bent the tree branch. / She has bent many branches while gardening.",
    "frontDesc": "Eu me inclino para alcançar. / Ela entortou o galho da árvore. / Ela já entortou muitos galhos enquanto jardina."
  },
  {
    "backDesc": "I bet that you'll arrive on time. / He bet money. / He has bet on many races.",
    "frontDesc": "Eu aposto que você vai chegar na hora. / Ele apostou dinheiro. / Ele já apostou em muitas corridas."
  },
  {
    "backDesc": "I bid on the artwork. / She bid an offer. / She has bid on several pieces of art.",
    "frontDesc": "Eu dei um lance na obra de arte. / Ela fez uma oferta. / Ela já deu lances em várias peças de arte."
  },
  {
    "backDesc": "I bind my shoes before leaving. / He bound the package. / He has bound multiple packages for shipping.",
    "frontDesc": "Eu amarro meus sapatos antes de sair. / Ele amarrou o pacote. / Ele já amarrou vários pacotes para envio."
  },
  {
    "backDesc": "I bite an apple for breakfast. / She bit her finger. / She has bitten her nails many times.",
    "frontDesc": "Eu mordo uma maçã no café da manhã. / Ela mordeu o dedo. / Ela já roeu as unhas muitas vezes."
  },
  {
    "backDesc": "My wound bleeds heavily. / He bled after the fall. / He has bled from similar wounds before.",
    "frontDesc": "Meu ferimento sangra muito. / Ele sangrou depois da queda. / Ele já sangrou com ferimentos semelhantes antes."
  },
  {
    "backDesc": "I blow out the candle on the cake. / He blew up the balloon. / He has blown many balloons for parties.",
    "frontDesc": "Eu sopro a vela do bolo. / Ele encheu o balão. / Ele já encheu muitos balões para festas."
  },
  {
    "backDesc": "I breed dogs at home. / She bred horses on the farm. / She has bred different animals over the years.",
    "frontDesc": "Eu crio cães em casa. / Ela criou cavalos na fazenda. / Ela já criou diferentes animais ao longo dos anos."
  },
  {
    "backDesc": "I broadcast a radio show. / He broadcast the news live. / He has broadcast important announcements recently.",
    "frontDesc": "Eu transmito um programa de rádio. / Ele transmitiu as notícias ao vivo. / Ele tem transmitido anúncios importantes recentemente."
  },
  {
    "backDesc": "I burn a candle during dinner. / She burnt the papers in the furnace. / She has burnt old letters before.",
    "frontDesc": "Eu acendo uma vela durante o jantar. / Ela queimou os papéis na fornalha. / Ela já queimou cartas antigas antes."
  },
  {
    "backDesc": "I burst the balloon during play. / He burst into laughter. / He has burst into laughter many times.",
    "frontDesc": "Eu estouro o balão durante a brincadeira. / Ele explodiu em risadas. / Ele já explodiu em risadas muitas vezes."
  },
  {
    "backDesc": "I forgive you for the mistake. / She forgave him for everything. / She has forgiven many people in her life.",
    "frontDesc": "Eu te perdoo pelo erro. / Ela o perdoou por tudo. / Ela já perdoou muitas pessoas na vida."
  },
  {
    "backDesc": "I freeze fruits for later. / He froze the water in the fridge. / He has frozen water for ice cubes.",
    "frontDesc": "Eu congelo frutas para depois. / Ele congelou a água na geladeira. / Ele tem congelado água para fazer gelo."
  },
  {
    "backDesc": "I clung to my mother during the storm. / He clung to his beliefs. / He has clung to them all this time.",
    "frontDesc": "Eu me agarrei à minha mãe durante a tempestade. / Ele se apegou às suas crenças. / Ele tem se apegado a elas todo esse tempo."
  },
  {
    "backDesc": "I creep through the grass to avoid being noticed. / She crept quietly. / She has crept in silently before.",
    "frontDesc": "Eu me arrasto pela grama para não ser notado(a). / Ela se arrastou silenciosamente. / Ela já se esgueirou em silêncio antes."
  },
  {
    "backDesc": "I deal in stocks on the market. / He dealt the goods in the store. / He has dealt in various products before.",
    "frontDesc": "Eu negocio ações no mercado. / Ele comercializou os produtos na loja. / Ele já lidou com vários produtos antes."
  },
  {
    "backDesc": "I dig a trench in the garden. / She dug to the well. / She has dug many holes for planting.",
    "frontDesc": "Eu cavo uma trincheira no jardim. / Ela cavou até o poço. / Ela já cavou muitos buracos para plantio."
  },
  {
    "backDesc": "I alighted on a bench in the park. / He alit on the hill. / He has alighted there a few times.",
    "frontDesc": "Eu me sentei (desembarquei) em um banco no parque. / Ele pousou na colina. / Ele já parou lá algumas vezes."
  },
  {
    "backDesc": "Misfortune befell that family. / He befell bad luck. / Bad luck has befallen him recently.",
    "frontDesc": "O infortúnio atingiu aquela família. / Aconteceu má sorte com ele. / Má sorte o atingiu recentemente."
  },
  {
    "backDesc": "Every person can beget offspring. / He begot an heir. / He has begotten two children.",
    "frontDesc": "Toda pessoa pode gerar descendentes. / Ele gerou um herdeiro. / Ele já gerou dois filhos."
  },
  {
    "backDesc": "I behold the sunset. / She beheld a beautiful landscape. / She has beheld many breathtaking views.",
    "frontDesc": "Eu contemplo o pôr do sol. / Ela contemplou uma paisagem linda. / Ela já contemplou muitas vistas de tirar o fôlego."
  },
  {
    "backDesc": "I beseech you for help. / He besought forgiveness. / He has besought kindness on many occasions.",
    "frontDesc": "Eu lhe suplico ajuda. / Ele suplicou perdão. / Ele já suplicou por bondade em muitas ocasiões."
  },
  {
    "backDesc": "He was beset by financial problems. / He beset his targets. / He has beset them with challenges.",
    "frontDesc": "Ele foi atormentado por problemas financeiros. / Ele cercou seus alvos. / Ele já os cercou de desafios."
  },
  {
    "backDesc": "Parents chided the child for disobedience. / He chided him publicly. / He has chidden him for his behavior.",
    "frontDesc": "Os pais repreenderam a criança por desobediência. / Ele o repreendeu publicamente. / Ele já o repreendeu por seu comportamento."
  },
  {
    "backDesc": "I clothe myself for winter. / She clad herself elegantly. / She has clad herself in fine clothes before.",
    "frontDesc": "Eu me visto para o inverno. / Ela se vestiu elegantemente. / Ela já se vestiu com roupas finas antes."
  },
  {
    "backDesc": "I dream of vacations. / He dreamt of a trip. / He has dreamt about traveling the world.",
    "frontDesc": "Eu sonho com férias. / Ele sonhou com uma viagem. / Ele já sonhou em viajar pelo mundo."
  },
  {
    "backDesc": "I feed the dog every day. / She fed the birds in the garden. / She has fed them every morning.",
    "frontDesc": "Eu alimento o cachorro todos os dias. / Ela alimentou os pássaros no jardim. / Ela os tem alimentado todas as manhãs."
  },
  {
    "backDesc": "This shirt fits me perfectly. / He fit into the team. / He has fit in well since day one.",
    "frontDesc": "Esta camisa me serve perfeitamente. / Ele se encaixou na equipe. / Ele tem se encaixado bem desde o primeiro dia."
  },
  {
    "backDesc": "I flee from the rain. / She fled from home. / She has fled difficult situations before.",
    "frontDesc": "Eu fujo da chuva. / Ela fugiu de casa. / Ela já fugiu de situações difíceis antes."
  },
  {
    "backDesc": "I fling a stone into the water. / He flung the bottle out the window. / He has flung objects in anger before.",
    "frontDesc": "Eu atiro uma pedra na água. / Ele jogou a garrafa pela janela. / Ele já arremessou objetos com raiva antes."
  },
  {
    "backDesc": "I forbid smoking in the building. / She forbade the children from watching TV. / She has forbidden them multiple times.",
    "frontDesc": "Eu proíbo fumar no prédio. / Ela proibiu as crianças de assistir TV. / Ela já proibiu várias vezes."
  },
  {
    "backDesc": "I forecast rain for tomorrow. / He forecast a price increase. / He has forecast such changes accurately.",
    "frontDesc": "Eu prevejo chuva para amanhã. / Ele previu um aumento de preço. / Ele tem previsto essas mudanças com precisão."
  },
  {
    "backDesc": "I forsake old habits. / She forsook her dreams. / She has forsaken them all.",
    "frontDesc": "Eu abandono velhos hábitos. / Ela abandonou os sonhos. / Ela já os abandonou completamente."
  },
  {
    "backDesc": "I kneel before the altar. / He knelt in a gesture of respect. / He has knelt there many times.",
    "frontDesc": "Eu me ajoelho diante do altar. / Ele se ajoelhou em um gesto de respeito. / Ele já se ajoelhou lá muitas vezes."
  },
  {
    "backDesc": "I knit a sweater for winter. / She knitted a scarf. / She has knitted many scarves before.",
    "frontDesc": "Eu tricoto um suéter para o inverno. / Ela tricotou um cachecol. / Ela já tricotou muitos cachecóis antes."
  },
  {
    "backDesc": "I lay the book on the table. / She laid the keys on the shelf. / She has laid them there many times.",
    "frontDesc": "Eu coloco o livro sobre a mesa. / Ela colocou as chaves na prateleira. / Ela já as colocou lá muitas vezes."
  },
  {
    "backDesc": "I lead the team. / He led the company for many years. / He has led numerous successful projects.",
    "frontDesc": "Eu lidero a equipe. / Ele liderou a empresa por muitos anos. / Ele já liderou inúmeros projetos bem-sucedidos."
  },
  {
    "backDesc": "I lean over the book. / He leant over the table. / He has leaned over it for hours.",
    "frontDesc": "Eu me inclino sobre o livro. / Ele se inclinou sobre a mesa. / Ele já ficou inclinado sobre ela por horas."
  },
  {
    "backDesc": "I leap on the rope. / He leapt over the fence. / He has leapt across many obstacles.",
    "frontDesc": "Eu salto na corda. / Ele saltou a cerca. / Ele já saltou muitos obstáculos."
  },
  {
    "backDesc": "I light the room's light. / He lit the light in the evening. / He has lit it every night since then.",
    "frontDesc": "Eu acendo a luz do quarto. / Ele acendeu a luz à noite. / Ele a acende todas as noites desde então."
  },
  {
    "backDesc": "I mistake in the calculations. / He mistook the decision. / He has mistaken people's intentions before.",
    "frontDesc": "Eu cometo erros nos cálculos. / Ele interpretou a decisão de forma errada. / Ele já se enganou sobre as intenções das pessoas antes."
  },
  {
    "backDesc": "I mow the grass in the garden. / He mowed the lawn yesterday. / He has mown it regularly.",
    "frontDesc": "Eu corto a grama do jardim. / Ele cortou o gramado ontem. / Ele o tem cortado regularmente."
  },
  {
    "backDesc": "I overcome difficulties every day. / He overcame his fears. / He has overcome many obstacles.",
    "frontDesc": "Eu supero dificuldades todos os dias. / Ele superou seus medos. / Ele já superou muitos obstáculos."
  },
  {
    "backDesc": "I partake in meetings. / He partook in the conference. / He has partaken in several events recently.",
    "frontDesc": "Eu participo de reuniões. / Ele participou da conferência. / Ele tem participado de vários eventos recentemente."
  },
  {
    "backDesc": "I plead for help. / He pled for forgiveness. / He has pled for mercy many times.",
    "frontDesc": "Eu imploro por ajuda. / Ele implorou por perdão. / Ele já implorou por misericórdia muitas vezes."
  },
  {
    "backDesc": "I prove my innocence. / He proved his theory. / He has proven it beyond doubt.",
    "frontDesc": "Eu provo minha inocência. / Ele provou sua teoria. / Ele a comprovou sem deixar dúvidas."
  },
  {
    "backDesc": "I saw wood in the workshop. / He sawed planks for a new boat. / He has sawn many pieces of wood.",
    "frontDesc": "Eu serro madeira na oficina. / Ele serrou tábuas para um novo barco. / Ele já serrour muitas peças de madeira."
  },
  {
    "backDesc": "I seek the keys at home. / He sought a solution to the problem. / He has sought answers everywhere.",
    "frontDesc": "Eu procuro as chaves em casa. / Ele procurou uma solução para o problema. / Ele já buscou respostas em todos os lugares."
  },
  {
    "backDesc": "I sew clothes in my atelier. / He sewed a shirt for several hours. / He has sewn many garments.",
    "frontDesc": "Eu costuro roupas no meu ateliê. / Ele costurou uma camisa por várias horas. / Ele já costurou muitas peças de roupa."
  },
  {
    "backDesc": "I shear sheep on the farm. / He sheared a sheep yesterday. / He has shorn many sheep this season.",
    "frontDesc": "Eu tosquio ovelhas na fazenda. / Ele tosquiou uma ovelha ontem. / Ele já tosquiou muitas ovelhas nesta temporada."
  },
  {
    "backDesc": "My sweater shrinks after washing. / It shrank in high temperature. / It has shrunk too much.",
    "frontDesc": "Meu suéter encolhe depois de lavar. / Ele encolheu em alta temperatura. / Ele encolheu demais."
  },
  {
    "backDesc": "I slay rodents in the basement. / He slew the monster in the forest. / He has slain many creatures in his stories.",
    "frontDesc": "Eu mato roedores no porão. / Ele matou o monstro na floresta. / Ele já matou muitas criaturas em suas histórias."
  },
  {
    "backDesc": "The kitchen stinks of rotten food. / It stank after a hot day. / It has stunk for hours.",
    "frontDesc": "A cozinha fede a comida podre. / Ela fedia depois de um dia quente. / Está fedendo há horas."
  },
  {
    "backDesc": "I stride with confidence. / He strode quickly, arriving on time. / He has stridden through many challenges.",
    "frontDesc": "Eu caminho com confiança. / Ele caminhou rapidamente, chegando pontualmente. / Ele já percorreu muitos desafios com firmeza."
  },
  {
    "backDesc": "I strike the ball towards the goal. / He struck the door hard. / He has struck fear into his opponents.",
    "frontDesc": "Eu chuto (ou bato) a bola em direção ao gol. / Ele bateu forte na porta. / Ele já impôs medo em seus adversários."
  },
  {
    "backDesc": "I string beads on a string. / He strung the lamp on the wall. / He has strung decorations before.",
    "frontDesc": "Eu enfio contas em um barbante. / Ele pendurou a lâmpada na parede. / Ele já pendurou decorações antes."
  },
  {
    "backDesc": "I strive to achieve the goal. / He strove for success for years. / He has striven to reach the top.",
    "frontDesc": "Eu me esforço para atingir o objetivo. / Ele se esforçou por sucesso durante anos. / Ele tem se empenhado para chegar ao topo."
  },
  {
    "backDesc": "I swing on the swing. / He swung on the balcony. / He has swung on that rope many times.",
    "frontDesc": "Eu balanço no balanço. / Ele se balançou na varanda. / Ele já se balançou naquela corda muitas vezes."
  },
  {
    "backDesc": "I tear the paper to shred it. / He tore the canvas with a knife. / He has torn many papers accidentally.",
    "frontDesc": "Eu rasgo o papel para picá-lo. / Ele rasgou a tela com uma faca. / Ele já rasgou muitos papéis acidentalmente."
  },
  {
    "backDesc": "I thrust the door to open it. / He thrust the door hard. / He has thrust it open before.",
    "frontDesc": "Eu empurro a porta para abri-la. / Ele empurrou a porta com força. / Ele já a empurrou para abrir antes."
  },
  {
    "backDesc": "I tread carefully on the wet floor. / He trod with a confident stride. / He has trodden this path before.",
    "frontDesc": "Eu piso com cuidado no chão molhado. / Ele pisou com passos confiantes. / Ele já percorreu este caminho antes."
  },
  {
    "backDesc": "I undo the move I made. / He undid the changes in the document. / He has undone them completely.",
    "frontDesc": "Eu desfaço o movimento que fiz. / Ele desfez as alterações no documento. / Ele já as desfez completamente."
  },
  {
    "backDesc": "I weave a scarf on the knitting needles. / He wove a rug in his workshop. / He has woven several rugs now.",
    "frontDesc": "Eu teço um cachecol nas agulhas de tricô. / Ele teceu um tapete em sua oficina. / Ele já teceu vários tapetes agora."
  },
  {
    "backDesc": "I weep in sorrow. / He wept after the breakup. / He has wept many tears.",
    "frontDesc": "Eu choro de tristeza. / Ele chorou depois do término. / Ele já derramou muitas lágrimas."
  },
  {
    "backDesc": "I wind the watch every morning. / He wound the strings into a tape. / He has wound them neatly.",
    "frontDesc": "Eu dou corda no relógio toda manhã. / Ele enrolou as cordas numa fita. / Ele já as enrolou cuidadosamente."
  },
  {
    "backDesc": "I withdraw from the discussion. / He withdrew from the project. / He has withdrawn completely.",
    "frontDesc": "Eu me retiro da discussão. / Ele se retirou do projeto. / Ele se afastou completamente."
  },
  {
    "backDesc": "I withstand difficult conditions. / He withstood the strong wind. / He has withstood many storms.",
    "frontDesc": "Eu suporto condições difíceis. / Ele suportou o vento forte. / Ele já resistiu a muitas tempestades."
  },
  {
    "backDesc": "I wring out wet towels. / He wrung juice out of fruits. / He has wrung out many towels.",
    "frontDesc": "Eu torço toalhas molhadas. / Ele espremeu suco das frutas. / Ele já torceu muitas toalhas."
  },
  {
    "backDesc": "I freeze food in the freezer. / He froze water for the freezer. / He has frozen enough water for ice.",
    "frontDesc": "Eu congelo comida no freezer. / Ele congelou água para o freezer. / Ele já congelou água suficiente para fazer gelo."
  },
  {
    "backDesc": "I hang a picture on the wall. / He hung the lamp in the room. / He has hung many pictures around the house.",
    "frontDesc": "Eu penduro um quadro na parede. / Ele pendurou a lâmpada no quarto. / Ele já pendurou muitos quadros pela casa."
  }
]
